diresa_torch/__init__.py
diresa_torch/arch/config.py
diresa_torch/arch/models.py
diresa_torch/arch/modules.py
diresa_torch/losses/__init__.py
diresa_torch/losses/loss_funcs.py
diresa_torch/training/__init__.py
diresa_torch/training/trainer.py
diresa_torch/utils/__init__.py
diresa_torch/utils/latent.py
diresa_torch/utils/utils.py
diresa_torch-1.2.1.dist-info/METADATA
diresa_torch-1.2.1.dist-info/WHEEL
diresa_torch-1.2.1.dist-info/licenses/LICENSE
diresa_torch-1.2.1.dist-info/RECORD
