Metadata-Version: 2.4
Name: diresa-torch
Version: 1.2.1
Summary: Diresa - distance-regularized siamese twin autoencoder
Project-URL: Homepage, https://gitlab.com/etrovub/ai4wcm/public/diresa-torch
Project-URL: Issues, https://gitlab.com/etrovub/ai4wcm/public/diresa-torch/-/issues
Author-email: Lars Bonnefoy <lars.bonnefoy@vub.be>, Janne Lisa Bouillon <janne.lisa.bouillon@vub.be>, Geert De Paepe <geert.de.paepe@vub.be>
License-File: LICENSE
Keywords: climate,learning,machine,pytorch,weather
Classifier: Development Status :: 4 - Beta
Classifier: Intended Audience :: Science/Research
Classifier: License :: OSI Approved :: MIT License
Classifier: Operating System :: OS Independent
Classifier: Programming Language :: Python :: 3
Classifier: Topic :: Scientific/Engineering :: Artificial Intelligence
Requires-Python: >=3.9
Requires-Dist: torch>=2.1
